xiaochuanipproxy/__init__.py
xiaochuanipproxy/api.py
xiaochuanipproxy/filter.py
xiaochuanipproxy/getip.py
xiaochuanipproxy/pic.py
xiaochuanipproxy/start.py
xiaochuanipproxy-0.0.1.dist-info/LICENSE
xiaochuanipproxy-0.0.1.dist-info/METADATA
xiaochuanipproxy-0.0.1.dist-info/WHEEL
xiaochuanipproxy-0.0.1.dist-info/top_level.txt
xiaochuanipproxy-0.0.1.dist-info/RECORD
